pntools/__init__.py
pntools/lpo_viewer.py
pntools/lpo_viewer_tk.py
pntools/partialorder.py
pntools/partialorder_renderer.py
pntools/petrinet.py
pntools/petrinet_renderer.py
pntools/petrinet_viewer_tk.py
pntools-0.3.1.dist-info/LICENSE
pntools-0.3.1.dist-info/METADATA
pntools-0.3.1.dist-info/WHEEL
pntools-0.3.1.dist-info/top_level.txt
pntools-0.3.1.dist-info/RECORD
