Metadata-Version: 2.1
Name: pntools
Version: 0.3.1
Summary: Petri net and labelled partial order tools
Home-page: https://github.com/irgangla/pntools
Author: Thomas Irgang
Author-email: pntools@irgang-la.com
License: MIT
Keywords: Petri net labelled partial order pnml lpo
Platform: UNKNOWN
Classifier: Development Status :: 3 - Alpha
Classifier: License :: OSI Approved :: MIT License
Classifier: Programming Language :: Python :: 3
